deepaas/__init__.py
deepaas/api/__init__.py
deepaas/api/v2/__init__.py
deepaas/api/v2/debug.py
deepaas/api/v2/models.py
deepaas/api/v2/predict.py
deepaas/api/v2/responses.py
deepaas/api/v2/train.py
deepaas/api/v2/utils.py
deepaas/api/versions.py
deepaas/cmd/__init__.py
deepaas/cmd/_shutdown.py
deepaas/cmd/cli.py
deepaas/cmd/execute.py
deepaas/cmd/run.py
deepaas/config.py
deepaas/exceptions.py
deepaas/model/__init__.py
deepaas/model/loading.py
deepaas/model/v2/__init__.py
deepaas/model/v2/base.py
deepaas/model/v2/test.py
deepaas/model/v2/wrapper.py
deepaas/opts.py
deepaas/tests/__init__.py
deepaas/tests/base.py
deepaas/tests/fake_responses.py
deepaas/tests/test_cmd.py
deepaas/tests/test_v2_api.py
deepaas/tests/test_v2_models.py
deepaas/tests/test_versions_api.py
deepaas-2.6.0.dist-info/LICENSE
deepaas-2.6.0.dist-info/METADATA
deepaas-2.6.0.dist-info/WHEEL
deepaas-2.6.0.dist-info/entry_points.txt
deepaas-2.6.0.dist-info/RECORD
