Metadata-Version: 2.1
Name: deepaas
Version: 2.6.0
Summary: DEEPaaS is a REST API to expose a machine learning model.
Home-page: https://github.com/ai4os/deepaas
License: Apache-2
Author: Alvaro Lopez Garcia
Author-email: aloga@ifca.unican.es
Requires-Python: >=3.6,<4.0
Classifier: Development Status :: 5 - Production/Stable
Classifier: Environment :: Console
Classifier: Environment :: Web Environment
Classifier: Framework :: AsyncIO
Classifier: Intended Audience :: Developers
Classifier: Intended Audience :: Information Technology
Classifier: Intended Audience :: Science/Research
Classifier: Intended Audience :: System Administrators
Classifier: License :: OSI Approved :: Apache Software License
Classifier: License :: Other/Proprietary License
Classifier: Operating System :: OS Independent
Classifier: Programming Language :: Python
Classifier: Programming Language :: Python :: 3
Classifier: Programming Language :: Python :: 3.6
Classifier: Programming Language :: Python :: 3.7
Classifier: Programming Language :: Python :: 3.8
Classifier: Programming Language :: Python :: 3.9
Classifier: Programming Language :: Python :: 3.10
Classifier: Programming Language :: Python :: 3.11
Classifier: Programming Language :: Python :: 3.12
Classifier: Topic :: Internet :: WWW/HTTP
Classifier: Topic :: Scientific/Engineering :: Artificial Intelligence
Classifier: Topic :: Scientific/Engineering :: Image Recognition
Classifier: Topic :: Scientific/Engineering :: Information Analysis
Classifier: Topic :: Scientific/Engineering :: Interface Engine/Protocol Translator
Requires-Dist: Werkzeug (>=2.0.3,<3.0.0)
Requires-Dist: aiohttp (>=3.8.6,<4.0.0)
Requires-Dist: aiohttp-apispec (>=2.2.3,<3.0.0)
Requires-Dist: marshmallow (>=3.14.1,<4.0.0)
Requires-Dist: oslo.config (>=8.8.1,<9.0.0)
Requires-Dist: oslo.log (>=4.8.0,<5.0.0)
Requires-Dist: stevedore (>=3.5.2,<4.0.0)
Requires-Dist: webargs (<6.0.0)
Project-URL: Bug Tracker, https://github.com/ai4os/deepaas/issues
Project-URL: Documentation, https://deepaas.readthedocs.io/
Project-URL: Repository, https://github.com/ai4os/deepaas/issues
